cpac/__init__.py
cpac/__main__.py
cpac/backends/__init__.py
cpac/backends/apptainer/__init__.py
cpac/backends/apptainer/apptainer.py
cpac/backends/apptainer/spython.py
cpac/backends/docker.py
cpac/backends/platform.py
cpac/backends/singularity.py
cpac/helpers/__init__.py
cpac/helpers/cpac_parse_resources.py
cpac/helpers/cpac_read_crash.py
cpac/utils/__init__.py
cpac/utils/bare_wrap.py
cpac/utils/checks.py
cpac/utils/utils.py
cpac-1.8.7.dist-info/AUTHORS.rst
cpac-1.8.7.dist-info/LICENSE.txt
cpac-1.8.7.dist-info/METADATA
cpac-1.8.7.dist-info/WHEEL
cpac-1.8.7.dist-info/entry_points.txt
cpac-1.8.7.dist-info/RECORD
