Metadata-Version: 2.1
Name: cpac
Version: 1.8.7
Summary: C-PAC Python Package
Home-page: https://github.com/FCP-INDI/cpac
License: MIT
Author: C-PAC developers
Author-email: cpac@cnl.childmind.org
Requires-Python: >=3.10,<4.0
Classifier: Development Status :: 3 - Alpha
Classifier: Intended Audience :: Science/Research
Classifier: License :: OSI Approved :: MIT License
Classifier: Natural Language :: English
Classifier: Operating System :: OS Independent
Classifier: Programming Language :: Python :: 3
Classifier: Programming Language :: Python :: 3.10
Classifier: Programming Language :: Python :: 3.11
Classifier: Programming Language :: Python :: 3.12
Classifier: Topic :: Scientific/Engineering :: Bio-Informatics
Provides-Extra: dev
Provides-Extra: gradients
Provides-Extra: testing
Provides-Extra: tsconcat
Requires-Dist: alabaster ; extra == "testing"
Requires-Dist: ba-tsconcat (>=0.1.2,<0.2.0) ; (python_version >= "3.11" and python_version < "4.0") and (extra == "tsconcat")
Requires-Dist: bids2table (==0.1.0b0) ; extra == "tsconcat"
Requires-Dist: coveralls ; extra == "dev"
Requires-Dist: docker (>=4.2.1)
Requires-Dist: docker-pycreds
Requires-Dist: dockerpty
Requires-Dist: elbow (==0.1.1) ; extra == "tsconcat"
Requires-Dist: imagesize ; extra == "testing"
Requires-Dist: nibabel (==5.2.1) ; extra == "tsconcat"
Requires-Dist: pandas (==2.2.2) ; python_version >= "3.11" and python_version < "4.0" and extra == "tsconcat"
Requires-Dist: pandas (>=0.23.4)
Requires-Dist: poetry (>=1.8.2)
Requires-Dist: pyarrow (==16.0.0) ; extra == "tsconcat"
Requires-Dist: pytest ; extra == "dev" or extra == "testing"
Requires-Dist: pytest-cov ; extra == "testing"
Requires-Dist: pytest-remotedata (>=0.3.2) ; extra == "dev"
Requires-Dist: pytest-runner ; extra == "dev" or extra == "testing"
Requires-Dist: pyyaml
Requires-Dist: rich
Requires-Dist: semver
Requires-Dist: sphinx ; extra == "dev" or extra == "testing"
Requires-Dist: spython (>=0.3.0)
Requires-Dist: tabulate (>=0.8.6)
Requires-Dist: tornado
Requires-Dist: websocket-client
Project-URL: Documentation, https://fcp-indi.github.io/docs/latest/user/cpac
Project-URL: Repository, https://github.com/FCP-INDI/cpac
